Metadata-Version: 2.1
Name: pyrebase-modific
Version: 1.2
Summary: Pyrebase modification with lists
Home-page: UNKNOWN
Author-email: lepeshokoff200@mail.ru
License: UNKNOWN
Keywords: Firebase
Platform: UNKNOWN
Classifier: Development Status :: 3 - Alpha
Classifier: Intended Audience :: Developers
Classifier: License :: OSI Approved :: MIT License
Classifier: Programming Language :: Python :: 3.4
